<annotation>
	<folder>Cropped</folder>
	<filename>cropped186.jpg</filename>
	<path>C:\Users\tanje\Desktop\Arrows\Cropped\cropped186.jpg</path>
	<source>
		<database>Unknown</database>
	</source>
	<size>
		<width>640</width>
		<height>540</height>
		<depth>3</depth>
	</size>
	<segmented>0</segmented>
	<object>
		<name>left</name>
		<pose>Unspecified</pose>
		<truncated>0</truncated>
		<difficult>0</difficult>
		<bndbox>
			<xmin>171</xmin>
			<ymin>184</ymin>
			<xmax>216</xmax>
			<ymax>220</ymax>
		</bndbox>
	</object>
	<object>
		<name>down</name>
		<pose>Unspecified</pose>
		<truncated>0</truncated>
		<difficult>0</difficult>
		<bndbox>
			<xmin>282</xmin>
			<ymin>197</ymin>
			<xmax>324</xmax>
			<ymax>235</ymax>
		</bndbox>
	</object>
	<object>
		<name>down</name>
		<pose>Unspecified</pose>
		<truncated>0</truncated>
		<difficult>0</difficult>
		<bndbox>
			<xmin>377</xmin>
			<ymin>193</ymin>
			<xmax>422</xmax>
			<ymax>233</ymax>
		</bndbox>
	</object>
	<object>
		<name>down</name>
		<pose>Unspecified</pose>
		<truncated>0</truncated>
		<difficult>0</difficult>
		<bndbox>
			<xmin>477</xmin>
			<ymin>188</ymin>
			<xmax>515</xmax>
			<ymax>222</ymax>
		</bndbox>
	</object>
</annotation>
