<annotation>
	<folder>Cropped</folder>
	<filename>cropped19.jpg</filename>
	<path>C:\Users\tanje\Desktop\Arrows\Cropped\cropped19.jpg</path>
	<source>
		<database>Unknown</database>
	</source>
	<size>
		<width>640</width>
		<height>540</height>
		<depth>3</depth>
	</size>
	<segmented>0</segmented>
	<object>
		<name>up</name>
		<pose>Unspecified</pose>
		<truncated>0</truncated>
		<difficult>0</difficult>
		<bndbox>
			<xmin>226</xmin>
			<ymin>213</ymin>
			<xmax>270</xmax>
			<ymax>254</ymax>
		</bndbox>
	</object>
	<object>
		<name>up</name>
		<pose>Unspecified</pose>
		<truncated>0</truncated>
		<difficult>0</difficult>
		<bndbox>
			<xmin>309</xmin>
			<ymin>201</ymin>
			<xmax>351</xmax>
			<ymax>239</ymax>
		</bndbox>
	</object>
	<object>
		<name>left</name>
		<pose>Unspecified</pose>
		<truncated>0</truncated>
		<difficult>0</difficult>
		<bndbox>
			<xmin>417</xmin>
			<ymin>204</ymin>
			<xmax>464</xmax>
			<ymax>244</ymax>
		</bndbox>
	</object>
	<object>
		<name>left</name>
		<pose>Unspecified</pose>
		<truncated>0</truncated>
		<difficult>0</difficult>
		<bndbox>
			<xmin>500</xmin>
			<ymin>195</ymin>
			<xmax>544</xmax>
			<ymax>234</ymax>
		</bndbox>
	</object>
</annotation>
